{
  "name": "Ben",
  "songs": [
    {
      "songname": "South",
      "artistname": "quannnic",
      "link": "https://www.youtube.com/watch?v=dWNtV7virhw"
    },
    {
      "songname": "Greedy",
      "artistname": "Tate McRae",
      "link": "https://www.youtube.com/watch?v=To4SWGZkEPk"
    },
    {
      "songname": "Seventyseven dog years",
      "artistname": "underscores",
      "link": "https://www.youtube.com/watch?v=CAcFzU3cPXY"
    },
    {
      "songname": "C’mon",
      "artistname": "Kesha",
      "link": "https://www.youtube.com/watch?v=c8A4QVop3-8"
    },
    {
      "songname": "10:36",
      "artistname": "beabadoobee",
      "link": "https://www.youtube.com/watch?v=0ZPXXqIsxsc"
    },
    {
      "songname": "Good God",
      "artistname": "daffo",
      "link": "https://www.youtube.com/watch?v=70e_OddhZCw"
    },
    {
      "songname": "Sprinx",
      "artistname": "nightmare friends",
      "link": "https://soundcloud.com/nightmarefriends/sprinx",
      "scArtUrl": "https://i1.sndcdn.com/artworks-3YBjB2h3K0RLPjdg-abqcEA-t500x500.jpg"
    },
    {
      "songname": "argyle",
      "artistname": "brakence",
      "link": "https://www.youtube.com/watch?v=hQrmtwhztnc"
    },
    {
      "songname": "Bubblegum",
      "artistname": "Club Eat",
      "link": "https://www.youtube.com/watch?v=BRuBB2xSTaw"
    },
    {
      "songname": "Gold Leaf",
      "artistname": "A. G. Cook",
      "link": "https://www.youtube.com/watch?v=cMRsOdBqvI0"
    },
    {
      "songname": "Royal Blue Walls",
      "artistname": "Jane Remover",
      "link": "https://www.youtube.com/watch?v=Z9Rbrch4hUs"
    },
    {
      "songname": "Biking (Solo)",
      "artistname": "Frank Ocean",
      "link": "https://www.youtube.com/watch?v=ZKY8-c5CRgU"
    },
    {
      "songname": "(You) On My Arm",
      "artistname": "Leith Ross",
      "link": "https://www.youtube.com/watch?v=wskzoEA66_k"
    },
    {
      "songname": "Snake Eyes EP",
      "artistname": "100 Gecs",
      "link": "https://www.youtube.com/watch?v=xrLKXshQmXU"
    },
    {
      "songname": "Runner",
      "artistname": "Alex G",
      "link": "https://www.youtube.com/watch?v=JFaMCIVHz2I"
    },
    {
      "songname": "Caring is Creepy",
      "artistname": "The Shins",
      "link": "https://www.youtube.com/watch?v=UqMbZY_iv6E"
    },
    {
      "songname": "Amoeba",
      "artistname": "Clairo",
      "link": "https://www.youtube.com/watch?v=VR8ooa3G_5M"
    },
    {
      "songname": "Title and Registration",
      "artistname": "Death Cab for Cutie",
      "link": "https://www.youtube.com/watch?v=1XmbvfxMiUE"
    },
    {
      "songname": "Person",
      "artistname": "Petal Supply",
      "link": "https://www.youtube.com/watch?v=vXwQ1uC2BqQ"
    },
    {
      "songname": "I Believe",
      "artistname": "Caroline Polachek",
      "link": "https://www.youtube.com/watch?v=ZXL_4Lv38nY"
    }
  ]
}