{
  "name": "Noa",
  "songs": [
    {
      "artistname": "Amantes del Futuro",
      "songname": "Cumbia Rosa",
      "link": "https://www.youtube.com/watch?v=-y5PQHmGOKo"
    },
    {
      "artistname": "Lex Amor & Seb Wildblood",
      "songname": "Night Ride",
      "link": "https://www.youtube.com/watch?v=98ir5it8MJs"
    },
    {
      "artistname": "Yoko Ono",
      "songname": "Have You Seen a Horizon Lately",
      "link": "https://www.youtube.com/watch?v=fabRmJh0eD0"
    },
    {
      "artistname": "LSDXOXO",
      "songname": "Freak",
      "link": "https://www.youtube.com/watch?v=yMzLWlGff7I"
    },
    {
      "artistname": "d4vd",
      "songname": "Separate",
      "link": "https://www.youtube.com/watch?v=yiwjT1hhsGE"
    },
    {
      "artistname": "Bob Marley & Lauryn Hill",
      "songname": "Turn your lights down low",
      "link": "https://www.youtube.com/watch?v=VitKvID-uvY"
    },
    {
      "artistname": "Aamu Kuu",
      "songname": "Vive La France",
      "link": "https://www.youtube.com/watch?v=tEc-YKYW1lI"
    },
    {
      "artistname": "Blood Orange",
      "songname": "Baby Florence (Figure)",
      "link": "https://www.youtube.com/watch?v=vFXvaz57mlE"
    },
    {
      "link": "https://www.youtube.com/watch?v=YdJekSd1-yU",
      "artistname": "John Glacier",
      "songname": "Icing"
    },
    {
      "link": "https://www.youtube.com/watch?v=z-J6MXgbvr8",
      "artistname": "Omar S",
      "songname": "Evergreen"
    },
    {
      "artistname": "Sally Oldfield",
      "songname": "Blue Water",
      "link": "https://www.youtube.com/watch?v=Y0vQsfcm38c"
    },
    {
      "songname": "Stolen Kiss of a Succubus",
      "artistname": " Fatima Al Qadiri",
      "link": "https://www.youtube.com/watch?v=IQbrFzhJ2hE"
    },
    {
      "artistname": "Mura Masa, Tirzah",
      "songname": "Today",
      "link": "https://www.youtube.com/watch?v=1DZlCMUVMvk"
    }
  ],
  "miscimages": [
    {
      "image": "/images/image.jpg"
    },
    {
      "image": "/images/image.png"
    }
  ]
}